clld_audio_plugin/__init__.py
clld_audio_plugin/datatables.py
clld_audio_plugin/maps.py
clld_audio_plugin/models.py
clld_audio_plugin/util.py
clld_audio_plugin/static/clld_audio_plugin.css
clld_audio_plugin/templates/clld_audio_plugin_util.mako
clld_audio_plugin/templates/language/snippet_html.mako
clld_audio_plugin-1.2.0.dist-info/LICENSE
clld_audio_plugin-1.2.0.dist-info/METADATA
clld_audio_plugin-1.2.0.dist-info/WHEEL
clld_audio_plugin-1.2.0.dist-info/top_level.txt
clld_audio_plugin-1.2.0.dist-info/RECORD
