Metadata-Version: 2.1
Name: clld-audio-plugin
Version: 1.2.0
Summary: Render linked audio files in clld apps.
Home-page: https://github.com/clld/clld-audio-plugin
Author: Robert Forkel
Author-email: dlce.rdm@eva.mpg.de
Project-URL: Bug Tracker, https://github.com/clld/clld-audio-plugin/issues
Classifier: Development Status :: 2 - Pre-Alpha
Classifier: Intended Audience :: Science/Research
Classifier: License :: OSI Approved :: Apache Software License
Classifier: Natural Language :: English
Classifier: Programming Language :: Python :: 3
Classifier: Programming Language :: Python :: 3.8
Classifier: Programming Language :: Python :: 3.9
Classifier: Programming Language :: Python :: 3.10
Classifier: Programming Language :: Python :: 3.11
Classifier: Programming Language :: Python :: 3.12
License-File: LICENSE
Requires-Dist: clld (>=7)
Requires-Dist: sqlalchemy
Requires-Dist: zope.interface
Provides-Extra: dev
Requires-Dist: flake8 ; extra == 'dev'
Requires-Dist: twine ; extra == 'dev'
Requires-Dist: wheel ; extra == 'dev'
Requires-Dist: build ; extra == 'dev'
Provides-Extra: test
Requires-Dist: pytest ; extra == 'test'
Requires-Dist: pytest-mock ; extra == 'test'
Requires-Dist: pytest-cov ; extra == 'test'
Requires-Dist: tox ; extra == 'test'
Requires-Dist: webtest ; extra == 'test'
